nice_gui_utils/__init__.py
nice_gui_utils/keycloak_js/__init__.py
nice_gui_utils/keycloak_js/keycloak.js
nice_gui_utils/keycloak_js/keycloak.py
nice_gui_utils/router/__init__.py
nice_gui_utils/router/router.py
nice_gui_utils/router/router_frame.js
nice_gui_utils-0.4.1.dist-info/LICENSE
nice_gui_utils-0.4.1.dist-info/METADATA
nice_gui_utils-0.4.1.dist-info/WHEEL
nice_gui_utils-0.4.1.dist-info/top_level.txt
nice_gui_utils-0.4.1.dist-info/RECORD
