Metadata-Version: 2.1
Name: nice_gui_utils
Version: 0.4.1
Summary: Utils to use with NiceGUI.
Author: Harter Kern
Project-URL: Repository, https://gitlab.com/harter-kern-public/nice-gui-utils
Project-URL: Bug Tracker, https://gitlab.com/harter-kern-public/nice-gui-utils/-/issues
Classifier: Programming Language :: Python :: 3
Classifier: License :: OSI Approved :: MIT License
Classifier: Operating System :: OS Independent
Requires-Python: >=3.9
License-File: LICENSE
Requires-Dist: nicegui >=1.4.0
